audiomatic/client.py
audiomatic_python-0.1.0.dist-info/LICENSE
audiomatic_python-0.1.0.dist-info/METADATA
audiomatic_python-0.1.0.dist-info/WHEEL
audiomatic_python-0.1.0.dist-info/top_level.txt
audiomatic_python-0.1.0.dist-info/RECORD
