Metadata-Version: 2.1
Name: audiomatic-python
Version: 0.1.0
Summary: Official Python client for the Audiomatic API
Requires-Python: >=3.9
License-File: LICENSE
Requires-Dist: filetype >=1.2.0
Requires-Dist: imageio-ffmpeg >=0.5.1
Requires-Dist: requests >=2.32.3
